{
  "repo": "google/angle",
  "branch": "main",
  "reviews": {
    "src/libANGLE/Error.cpp": {
      "checked": true,
      "ts": "2025-11-14T12:59:58.339Z"
    },
    "src/libANGLE/Error.h": {
      "checked": true,
      "ts": "2025-11-14T10:27:12.931Z"
    },
    "src/libANGLE/Fence.cpp": {
      "checked": true,
      "ts": "2025-11-14T13:00:00.115Z"
    },
    "src/libANGLE/Fence.h": {
      "checked": true,
      "ts": "2025-11-14T10:27:12.931Z"
    },
    "src/libANGLE/Image.cpp": {
      "checked": true,
      "ts": "2025-11-14T13:00:07.851Z"
    },
    "src/libANGLE/Image.h": {
      "checked": true,
      "ts": "2025-11-14T10:27:12.931Z"
    },
    "src/libANGLE/VaryingPacking.cpp": {
      "checked": true,
      "ts": "2025-11-14T13:01:19.684Z"
    },
    "src/libANGLE/VaryingPacking.h": {
      "checked": true,
      "ts": "2025-11-14T10:27:12.931Z"
    },
    "src/libANGLE/VertexArray.cpp": {
      "checked": true,
      "ts": "2025-11-14T13:01:20.907Z"
    },
    "src/libANGLE/VertexArray.h": {
      "checked": true,
      "ts": "2025-11-14T10:27:12.931Z"
    },
    "src/libANGLE/renderer/d3d/d3d11/Blit11.cpp": {
      "checked": true,
      "ts": "2025-11-14T13:02:25.714Z"
    },
    "src/libANGLE/renderer/d3d/d3d11/Blit11.h": {
      "checked": true,
      "ts": "2025-11-14T10:27:12.931Z"
    },
    "src/libANGLE/renderer/d3d/d3d11/Context11.cpp": {
      "checked": true,
      "ts": "2025-11-14T13:02:27.779Z"
    },
    "src/libANGLE/renderer/d3d/d3d11/Context11.h": {
      "checked": true,
      "ts": "2025-11-14T10:27:12.931Z"
    },
    "src/libANGLE/renderer/d3d/d3d11/Image11.cpp": {
      "checked": true,
      "ts": "2025-11-14T10:27:12.931Z"
    },
    "src/libANGLE/renderer/d3d/d3d11/Image11.h": {
      "checked": true,
      "ts": "2025-11-14T10:27:12.931Z"
    },
    "src/libANGLE/renderer/d3d/d3d11/Renderer11.h": {
      "checked": true,
      "ts": "2025-11-14T10:27:12.931Z"
    },
    "src/libANGLE/renderer/d3d/d3d11/Renderer11.cpp": {
      "checked": true,
      "ts": "2025-11-14T13:02:42.804Z"
    },
    "src/libANGLE/renderer/d3d/d3d11/TextureStorage11.cpp": {
      "checked": true,
      "ts": "2025-11-14T13:02:52.508Z"
    },
    "src/libANGLE/renderer/d3d/d3d11/TextureStorage11.h": {
      "checked": true,
      "ts": "2025-11-14T10:27:12.931Z"
    },
    "src/libANGLE/renderer/d3d/d3d11/VertexArray11.cpp": {
      "checked": true,
      "ts": "2025-11-14T13:02:56.300Z"
    },
    "src/libANGLE/Buffer.cpp": {
      "checked": true,
      "ts": "2025-11-14T12:59:43.804Z"
    },
    "src/libANGLE/Buffer.h": {
      "checked": true,
      "ts": "2025-11-14T10:27:12.931Z"
    },
    "src/libANGLE/Caps.h": {
      "checked": true,
      "ts": "2025-11-14T10:27:12.931Z"
    },
    "src/libANGLE/Compiler.cpp": {
      "checked": true,
      "ts": "2025-11-14T12:59:52.572Z"
    },
    "src/libANGLE/Compiler.h": {
      "checked": true,
      "ts": "2025-11-14T10:27:12.931Z"
    },
    "src/libANGLE/Context_gles_2_0_autogen.h": {
      "checked": true,
      "ts": "2025-11-14T10:27:12.931Z"
    },
    "src/libANGLE/Context_gles_3_0_autogen.h": {
      "checked": true,
      "ts": "2025-11-14T10:27:12.931Z"
    },
    "src/libANGLE/Context.cpp": {
      "checked": true,
      "ts": "2025-11-14T12:59:54.707Z"
    },
    "src/libANGLE/Context.h": {
      "checked": true,
      "ts": "2025-11-14T10:27:12.931Z"
    },
    "src/compiler/translator/ParseContext.cpp": {
      "checked": true,
      "ts": "2025-11-14T12:56:09.084Z"
    },
    "src/libANGLE/HandleAllocator.cpp": {
      "checked": true,
      "ts": "2025-11-14T13:00:06.523Z"
    },
    "src/libANGLE/HandleAllocator.h": {
      "checked": true,
      "ts": "2025-11-14T10:27:12.931Z"
    },
    "src/libANGLE/MemoryShaderCache.h": {
      "checked": true,
      "ts": "2025-11-14T10:27:12.931Z"
    },
    "src/libANGLE/MemoryShaderCache.cpp": {
      "checked": true,
      "ts": "2025-11-14T13:00:11.483Z"
    },
    "src/libANGLE/Program.cpp": {
      "checked": true,
      "ts": "2025-11-14T13:00:38.220Z"
    },
    "src/libANGLE/Program.h": {
      "checked": true,
      "ts": "2025-11-14T10:27:12.931Z"
    },
    "src/libANGLE/ProgramExecutable.cpp": {
      "checked": true,
      "ts": "2025-11-14T13:00:40.261Z"
    },
    "src/libANGLE/ProgramExecutable.h": {
      "checked": true,
      "ts": "2025-11-14T10:27:12.931Z"
    },
    "src/libANGLE/ProgramLinkedResources.cpp": {
      "checked": true,
      "ts": "2025-11-14T13:07:57.957Z"
    },
    "src/libANGLE/ProgramLinkedResources.h": {
      "checked": true,
      "ts": "2025-11-14T10:27:12.931Z"
    },
    "src/libANGLE/ResourceManager.cpp": {
      "checked": true,
      "ts": "2025-11-14T13:01:04.300Z"
    },
    "src/libANGLE/ResourceManager.h": {
      "checked": true,
      "ts": "2025-11-14T10:27:12.931Z"
    },
    "src/libANGLE/ResourceMap.h": {
      "checked": true,
      "ts": "2025-11-14T10:27:12.931Z"
    },
    "src/libANGLE/Sampler.cpp": {
      "checked": true,
      "ts": "2025-11-14T13:01:06.092Z"
    },
    "src/libANGLE/Sampler.h": {
      "checked": true,
      "ts": "2025-11-14T10:27:12.931Z"
    },
    "src/libANGLE/Shader.cpp": {
      "checked": true,
      "ts": "2025-11-14T13:01:07.108Z"
    },
    "src/libANGLE/Shader.h": {
      "checked": true,
      "ts": "2025-11-14T10:27:12.931Z"
    },
    "src/libANGLE/validationES.h": {
      "checked": true,
      "ts": "2025-11-14T10:27:12.931Z"
    },
    "src/libANGLE/validationES.cpp": {
      "checked": true,
      "ts": "2025-11-14T13:01:14.459Z"
    },
    "src/libANGLE/validationES1_autogen.h": {
      "checked": true,
      "ts": "2025-11-14T10:27:12.931Z"
    },
    "src/libANGLE/validationES1.cpp": {
      "checked": true,
      "ts": "2025-11-14T13:01:15.460Z"
    },
    "src/libANGLE/validationES1.h": {
      "checked": true,
      "ts": "2025-11-14T10:27:12.931Z"
    },
    "src/libANGLE/validationES2_autogen.h": {
      "checked": true,
      "ts": "2025-11-14T10:27:12.931Z"
    },
    "src/libANGLE/validationES2.cpp": {
      "checked": true,
      "ts": "2025-11-14T13:01:16.292Z"
    },
    "src/libANGLE/validationES2.h": {
      "checked": true,
      "ts": "2025-11-14T10:27:12.931Z"
    },
    "src/libANGLE/validationES3_autogen.h": {
      "checked": true,
      "ts": "2025-11-14T10:27:12.931Z"
    },
    "src/libANGLE/validationES3.cpp": {
      "checked": true,
      "ts": "2025-11-14T13:01:16.803Z"
    },
    "src/libANGLE/validationES3.h": {
      "checked": true,
      "ts": "2025-11-14T10:27:12.931Z"
    },
    "src/libANGLE/renderer/BufferImpl.h": {
      "checked": true,
      "ts": "2025-11-14T10:27:12.931Z"
    },
    "src/libANGLE/renderer/ContextImpl.cpp": {
      "checked": true,
      "ts": "2025-11-14T13:07:26.388Z"
    },
    "src/libANGLE/renderer/CompilerImpl.h": {
      "checked": true,
      "ts": "2025-11-14T10:27:12.931Z"
    },
    "src/libANGLE/renderer/ProgramImpl.cpp": {
      "checked": true,
      "ts": "2025-11-14T13:07:02.940Z"
    },
    "src/libANGLE/renderer/ShaderImpl.cpp": {
      "checked": true,
      "ts": "2025-11-14T13:07:04.948Z"
    },
    "src/libANGLE/renderer/ShaderImpl.h": {
      "checked": true,
      "ts": "2025-11-14T10:27:12.931Z"
    },
    "src/libANGLE/renderer/d3d/CompilerD3D.cpp": {
      "checked": true,
      "ts": "2025-11-14T13:01:39.412Z"
    },
    "src/libANGLE/renderer/d3d/CompilerD3D.h": {
      "checked": true,
      "ts": "2025-11-14T10:27:12.931Z"
    },
    "src/libANGLE/renderer/d3d/DynamicHLSL.h": {
      "checked": true,
      "ts": "2025-11-14T10:27:12.931Z"
    },
    "src/libANGLE/renderer/d3d/DynamicHLSL.cpp": {
      "checked": true,
      "ts": "2025-11-14T13:01:41.706Z"
    },
    "src/libANGLE/renderer/d3d/HLSLCompiler.cpp": {
      "checked": true,
      "ts": "2025-11-14T13:01:44.758Z"
    },
    "src/libANGLE/renderer/d3d/HLSLCompiler.h": {
      "checked": true,
      "ts": "2025-11-14T10:27:12.931Z"
    },
    "src/libANGLE/renderer/d3d/ProgramD3D.cpp": {
      "checked": true,
      "ts": "2025-11-14T13:01:52.460Z"
    },
    "src/libANGLE/renderer/d3d/ProgramD3D.h": {
      "checked": true,
      "ts": "2025-11-14T10:27:12.931Z"
    },
    "src/libANGLE/renderer/d3d/ProgramExecutableD3D.cpp": {
      "checked": true,
      "ts": "2025-11-14T13:01:53.315Z"
    },
    "src/libANGLE/renderer/d3d/RendererD3D.cpp": {
      "checked": true,
      "ts": "2025-11-14T13:01:55.818Z"
    },
    "src/libANGLE/renderer/d3d/ShaderD3D.h": {
      "checked": true,
      "ts": "2025-11-14T10:27:12.931Z"
    },
    "src/libANGLE/renderer/d3d/ShaderD3D.cpp": {
      "checked": true,
      "ts": "2025-11-14T13:01:57.187Z"
    },
    "src/libANGLE/renderer/d3d/ShaderExecutableD3D.cpp": {
      "checked": true,
      "ts": "2025-11-14T13:01:58.818Z"
    },
    "src/libANGLE/renderer/d3d/ShaderExecutableD3D.h": {
      "checked": true,
      "ts": "2025-11-14T10:27:12.931Z"
    },
    "src/libANGLE/renderer/d3d/d3d11/Program11.cpp": {
      "checked": true,
      "ts": "2025-11-14T13:02:40.565Z"
    },
    "src/libANGLE/renderer/d3d/d3d11/Program11.h": {
      "checked": true,
      "ts": "2025-11-14T10:27:12.931Z"
    },
    "src/compiler/translator/hlsl/ASTMetadataHLSL.cpp": {
      "checked": true,
      "ts": "2025-11-14T12:56:56.178Z"
    },
    "src/compiler/translator/hlsl/ASTMetadataHLSL.h": {
      "checked": true,
      "ts": "2025-11-14T10:27:12.931Z"
    },
    "src/compiler/translator/hlsl/BuiltInFunctionEmulatorHLSL.cpp": {
      "checked": true,
      "ts": "2025-11-14T12:57:02.875Z"
    },
    "src/compiler/translator/hlsl/BuiltInFunctionEmulatorHLSL.h": {
      "checked": true,
      "ts": "2025-11-14T10:27:12.931Z"
    },
    "src/compiler/translator/hlsl/emulated_builtin_functions_hlsl_autogen.cpp": {
      "checked": true,
      "ts": "2025-11-14T12:57:04.603Z"
    },
    "src/compiler/translator/hlsl/OutputHLSL.cpp": {
      "checked": true,
      "ts": "2025-11-14T12:57:06.180Z"
    },
    "src/compiler/translator/hlsl/OutputHLSL.h": {
      "checked": true,
      "ts": "2025-11-14T10:27:12.931Z"
    },
    "src/compiler/translator/hlsl/ResourcesHLSL.cpp": {
      "checked": true,
      "ts": "2025-11-14T12:57:07.836Z"
    },
    "src/compiler/translator/hlsl/ResourcesHLSL.h": {
      "checked": true,
      "ts": "2025-11-14T10:27:12.931Z"
    },
    "src/compiler/translator/hlsl/ShaderStorageBlockFunctionHLSL.cpp": {
      "checked": true,
      "ts": "2025-11-14T12:57:11.372Z"
    },
    "src/compiler/translator/hlsl/ShaderStorageBlockFunctionHLSL.h": {
      "checked": true,
      "ts": "2025-11-14T10:27:12.931Z"
    },
    "src/compiler/translator/hlsl/ShaderStorageBlockOutputHLSL.cpp": {
      "checked": true,
      "ts": "2025-11-14T12:57:12.194Z"
    },
    "src/compiler/translator/hlsl/ShaderStorageBlockOutputHLSL.h": {
      "checked": true,
      "ts": "2025-11-14T10:27:12.931Z"
    },
    "src/compiler/translator/hlsl/StructureHLSL.cpp": {
      "checked": true,
      "ts": "2025-11-14T12:57:14.668Z"
    },
    "src/compiler/translator/hlsl/StructureHLSL.h": {
      "checked": true,
      "ts": "2025-11-14T10:27:12.931Z"
    },
    "src/compiler/translator/glsl/OutputESSL.cpp": {
      "checked": true,
      "ts": "2025-11-14T12:56:44.068Z"
    },
    "src/compiler/translator/glsl/OutputGLSL.cpp": {
      "checked": true,
      "ts": "2025-11-14T12:56:45.674Z"
    },
    "src/compiler/translator/glsl/OutputESSL.h": {
      "checked": true,
      "ts": "2025-11-14T10:27:12.931Z"
    },
    "src/compiler/translator/glsl/OutputGLSL.h": {
      "checked": true,
      "ts": "2025-11-14T10:27:12.931Z"
    },
    "src/compiler/translator/glsl/OutputGLSLBase.cpp": {
      "checked": true,
      "ts": "2025-11-14T12:56:47.364Z"
    },
    "src/compiler/translator/glsl/OutputGLSLBase.h": {
      "checked": true,
      "ts": "2025-11-14T10:27:12.931Z"
    },
    "src/compiler/translator/glsl/TranslatorESSL.h": {
      "checked": true,
      "ts": "2025-11-14T10:27:12.931Z"
    },
    "src/compiler/translator/glsl/TranslatorGLSL.cpp": {
      "checked": true,
      "ts": "2025-11-14T12:56:49.405Z"
    },
    "src/compiler/translator/glsl/TranslatorGLSL.h": {
      "checked": true,
      "ts": "2025-11-14T10:27:12.931Z"
    },
    "src/compiler/translator/glsl/VersionGLSL.cpp": {
      "checked": true,
      "ts": "2025-11-14T12:56:50.203Z"
    },
    "src/compiler/translator/glsl/VersionGLSL.h": {
      "checked": true,
      "ts": "2025-11-14T10:27:12.931Z"
    },
    "src/libANGLE/renderer/metal/FrameBufferMtl.h": {
      "checked": true,
      "ts": "2025-11-14T10:27:12.931Z"
    },
    "src/libANGLE/renderer/metal/FrameBufferMtl.mm": {
      "checked": true,
      "ts": "2025-11-14T13:03:46.757Z"
    },
    "src/libANGLE/renderer/metal/mtl_command_buffer.h": {
      "checked": true,
      "ts": "2025-11-14T10:27:12.931Z"
    },
    "src/libANGLE/renderer/metal/mtl_command_buffer.mm": {
      "checked": true,
      "ts": "2025-11-14T13:03:50.971Z"
    },
    "src/libANGLE/renderer/metal/mtl_common.mm": {
      "checked": true,
      "ts": "2025-11-14T13:03:51.884Z"
    },
    "src/libANGLE/renderer/metal/mtl_common.h": {
      "checked": true,
      "ts": "2025-11-14T10:27:12.931Z"
    },
    "src/libANGLE/renderer/metal/mtl_library_cache.h": {
      "checked": true,
      "ts": "2025-11-14T10:27:12.931Z"
    },
    "src/libANGLE/renderer/metal/mtl_library_cache.mm": {
      "checked": true,
      "ts": "2025-11-14T13:03:54.997Z"
    },
    "src/libANGLE/renderer/metal/mtl_pipeline_cache.mm": {
      "checked": true,
      "ts": "2025-11-14T13:03:56.707Z"
    },
    "src/libANGLE/renderer/metal/mtl_pipeline_cache.h": {
      "checked": true,
      "ts": "2025-11-14T10:27:12.931Z"
    },
    "src/libANGLE/renderer/metal/mtl_state_cache.h": {
      "checked": true,
      "ts": "2025-11-14T10:27:12.931Z"
    },
    "src/libANGLE/renderer/metal/mtl_state_cache.mm": {
      "checked": true,
      "ts": "2025-11-14T13:04:02.549Z"
    },
    "src/libANGLE/renderer/metal/RenderBufferMtl.h": {
      "checked": true,
      "ts": "2025-11-14T10:27:12.931Z"
    },
    "src/libANGLE/renderer/metal/RenderBufferMtl.mm": {
      "checked": true,
      "ts": "2025-11-14T13:04:05.235Z"
    },
    "src/libANGLE/renderer/metal/TextureMtl.h": {
      "checked": true,
      "ts": "2025-11-14T10:27:12.931Z"
    },
    "src/libANGLE/renderer/metal/TextureMtl.mm": {
      "checked": true,
      "ts": "2025-11-14T13:04:16.355Z"
    },
    "src/libANGLE/renderer/metal/VertexArrayMtl.mm": {
      "checked": true,
      "ts": "2025-11-14T13:04:18.508Z"
    },
    "src/libANGLE/renderer/metal/VertexArrayMtl.h": {
      "checked": true,
      "ts": "2025-11-14T10:27:12.931Z"
    },
    "src/libANGLE/renderer/d3d/d3d11/Buffer11.cpp": {
      "checked": true,
      "ts": "2025-11-14T10:27:12.931Z"
    },
    "src/libANGLE/renderer/d3d/d3d11/Buffer11.h": {
      "checked": true,
      "ts": "2025-11-14T10:27:12.931Z"
    },
    "src/libANGLE/renderer/d3d/d3d11/Framebuffer11.cpp": {
      "checked": true,
      "ts": "2025-11-14T13:02:37.020Z"
    },
    "src/libANGLE/renderer/d3d/d3d11/Framebuffer11.h": {
      "checked": true,
      "ts": "2025-11-14T10:27:12.931Z"
    },
    "src/libANGLE/renderer/metal/renderermtl_utils.cpp": {
      "checked": true,
      "ts": "2025-11-14T13:04:09.509Z"
    },
    "src/libANGLE/renderer/metal/RenderTargetMtl.mm": {
      "checked": true,
      "ts": "2025-11-14T13:04:10.267Z"
    },
    "src/libANGLE/renderer/metal/RenderTargetMtl.h": {
      "checked": true,
      "ts": "2025-11-14T10:27:12.931Z"
    },
    "src/libANGLE/renderer/metal/renderermtl_utils.h": {
      "checked": true,
      "ts": "2025-11-14T10:27:12.931Z"
    },
    "src/libANGLE/renderer/metal/mtl_render_utils.h": {
      "checked": true,
      "ts": "2025-11-14T10:27:12.931Z"
    },
    "src/libANGLE/renderer/metal/mtl_render_utils.mm": {
      "checked": true,
      "ts": "2025-11-14T13:04:00.613Z"
    },
    "src/libANGLE/renderer/metal/BufferMtl.mm": {
      "checked": true,
      "ts": "2025-11-14T13:03:44.884Z"
    },
    "src/libANGLE/renderer/metal/BufferMtl.h": {
      "checked": true,
      "ts": "2025-11-14T10:27:12.931Z"
    },
    "src/compiler/translator/VariablePacker.cpp": {
      "checked": true,
      "ts": "2025-11-14T12:56:23.108Z"
    },
    "src/compiler/translator/Compiler.cpp": {
      "checked": true,
      "ts": "2025-11-14T12:55:49.484Z"
    },
    "src/compiler/translator/ValidateAST.cpp": {
      "checked": true,
      "ts": "2025-11-14T12:56:16.227Z"
    },
    "src/libANGLE/renderer/d3d/d3d11/Device11.cpp": {
      "checked": true,
      "ts": "2025-11-14T13:04:34.316Z"
    },
    "src/libANGLE/renderer/d3d/d3d11/Fence11.cpp": {
      "checked": true,
      "ts": "2025-11-14T13:02:31.612Z"
    },
    "src/libANGLE/renderer/d3d/d3d11/ShaderExecutable11.cpp": {
      "checked": true,
      "ts": "2025-11-14T13:02:45.812Z"
    },
    "src/libANGLE/renderer/d3d/d3d9/Blit9.cpp": {
      "checked": true,
      "ts": "2025-11-14T13:02:08.474Z"
    },
    "src/libANGLE/renderer/d3d/d3d9/Buffer9.cpp": {
      "checked": true,
      "ts": "2025-11-14T13:02:08.922Z"
    },
    "src/libANGLE/renderer/d3d/d3d9/Context9.cpp": {
      "checked": true,
      "ts": "2025-11-14T13:02:10.564Z"
    },
    "src/libANGLE/renderer/d3d/d3d9/Framebuffer9.cpp": {
      "checked": true,
      "ts": "2025-11-14T13:02:14.676Z"
    },
    "src/libANGLE/renderer/d3d/d3d9/Image9.cpp": {
      "checked": true,
      "ts": "2025-11-14T13:02:15.706Z"
    },
    "src/libANGLE/renderer/d3d/d3d9/ShaderExecutable9.cpp": {
      "checked": true,
      "ts": "2025-11-14T13:02:19.660Z"
    },
    "src/libANGLE/renderer/d3d/ImageD3D.cpp": {
      "checked": true,
      "ts": "2025-11-14T13:01:48.412Z"
    },
    "src/libANGLE/renderer/d3d/VertexBuffer.cpp": {
      "checked": true,
      "ts": "2025-11-14T13:02:02.008Z"
    },
    "src/libANGLE/renderer/d3d/TextureD3D.cpp": {
      "checked": true,
      "ts": "2025-11-14T13:02:00.899Z"
    },
    "src/libANGLE/renderer/gl/BlitGL.cpp": {
      "checked": true,
      "ts": "2025-11-14T13:06:10.267Z"
    },
    "src/libANGLE/Framebuffer.cpp": {
      "checked": true,
      "ts": "2025-11-14T13:00:02.149Z"
    },
    "src/libANGLE/VertexAttribute.cpp": {
      "checked": true,
      "ts": "2025-11-14T13:01:21.596Z"
    },
    "src/libANGLE/Texture.cpp": {
      "checked": true,
      "ts": "2025-11-14T13:01:08.947Z"
    },
    "src/libANGLE/TransformFeedback.cpp": {
      "checked": true,
      "ts": "2025-11-14T13:08:12.387Z"
    },
    "src/libANGLE/Caps.cpp": {
      "checked": true,
      "ts": "2025-11-14T12:59:45.133Z"
    },
    "src/libANGLE/renderer/d3d/d3d11/Clear11.cpp": {
      "checked": true,
      "ts": "2025-11-14T13:02:28.818Z"
    },
    "src/libANGLE/renderer/gl/renderergl_utils.cpp": {
      "checked": true,
      "ts": "2025-11-22T06:38:40.180Z"
    },
    "src/libANGLE/renderer/gl/ClearMultiviewGL.cpp": {
      "checked": true,
      "ts": "2025-11-22T06:54:04.653Z"
    },
    "src/libANGLE/renderer/gl/CompilerGL.cpp": {
      "checked": true,
      "ts": "2025-11-22T06:54:28.365Z"
    },
    "src/libANGLE/renderer/vulkan/AllocatorHelperPool.cpp": {
      "checked": true,
      "ts": "2025-11-22T07:09:33.613Z"
    },
    "src/libANGLE/renderer/vulkan/CommandQueue.cpp": {
      "checked": true,
      "ts": "2025-11-22T08:34:33.585Z"
    },
    "src/libANGLE/renderer/vulkan/CompilerVk.cpp": {
      "checked": true,
      "ts": "2025-11-22T08:34:47.064Z"
    },
    "src/libANGLE/renderer/vulkan/DebugAnnotatorVk.cpp": {
      "checked": true,
      "ts": "2025-11-24T09:56:53.462Z"
    },
    "src/libANGLE/renderer/vulkan/DeviceVk.cpp": {
      "checked": true,
      "ts": "2025-11-24T09:59:08.336Z"
    },
    "src/libANGLE/renderer/vulkan/DisplayVk.cpp": {
      "checked": true,
      "ts": "2025-11-24T10:07:58.339Z"
    },
    "src/libANGLE/renderer/vulkan/FenceNVVk.cpp": {
      "checked": true,
      "ts": "2025-11-24T10:11:34.081Z"
    },
    "src/libANGLE/renderer/vulkan/ImageVk.cpp": {
      "checked": true,
      "ts": "2025-11-24T10:19:06.671Z"
    }
  },
  "manual": [],
  "meta": {
    "version": 7,
    "updatedAt": 1764049768948
  }
}